pytest_pdb.py
pytest_pdb-0.3.1.dist-info/METADATA
pytest_pdb-0.3.1.dist-info/RECORD
pytest_pdb-0.3.1.dist-info/WHEEL
pytest_pdb-0.3.1.dist-info/entry_points.txt
pytest_pdb-0.3.1.dist-info/top_level.txt
