Metadata-Version: 2.1
Name: pytest-pdb
Version: 0.3.1
Summary: pytest plugin which adds pdb helper commands related to pytest.
Home-page: https://github.com/fschulze/pytest-pdb
Author: Florian Schulze
Author-email: florian.schulze@gmx.net
License: MIT license
Platform: UNKNOWN
Classifier: Framework :: Pytest
Requires-Dist: pytest
